finnemner/__init__.py
finnemner/finnemner.py
finnemner-1.0.2.dist-info/METADATA
finnemner-1.0.2.dist-info/WHEEL
finnemner-1.0.2.dist-info/top_level.txt
finnemner-1.0.2.dist-info/RECORD
