Metadata-Version: 2.1
Name: finnemner
Version: 1.0.2
Summary: nem and ner
Home-page: UNKNOWN
Author: WYRZL
Author-email: wuuyanru@163.com
License: Apache
Platform: UNKNOWN
